easy_kubeflow/__init__.py
easy_kubeflow/_docker/__init__.py
easy_kubeflow/_docker/docker_util.py
easy_kubeflow/examples/__init__.py
easy_kubeflow/pipelines/__init__.py
easy_kubeflow/pipelines/pipelines_util.py
easy_kubeflow/utils/__init__.py
easy_kubeflow/utils/log_util.py
easy_kubeflow-0.0.6.dist-info/METADATA
easy_kubeflow-0.0.6.dist-info/WHEEL
easy_kubeflow-0.0.6.dist-info/top_level.txt
easy_kubeflow-0.0.6.dist-info/RECORD
