Metadata-Version: 2.1
Name: easy-kubeflow
Version: 0.0.6
Summary: sdk help users for a better use of kubeflow
Home-page: https://service.stonewise.cn:8029/liuweibin/easy-kubeflow.git
Author: CrazyBean
Author-email: liuweibin@stonewise.cn
License: UNKNOWN
Platform: UNKNOWN
Classifier: Programming Language :: Python :: 3
Classifier: License :: OSI Approved :: MIT License
Classifier: Operating System :: OS Independent
Requires-Python: >=3.5
Requires-Dist: docker (>=4.2.1)
Requires-Dist: kfp (==1.3.0)
Requires-Dist: pandas (>=1.1.5)
Requires-Dist: tqdm (>=4.56.0)
